ReactInDepth/README.md
ReactInDepth/__init__.py
ReactInDepth/__main__.py
ReactInDepth/file.epub
ReactInDepth/index.html
ReactInDepth/css/__init__.py
ReactInDepth/css/annotations.css
ReactInDepth/css/main.css
ReactInDepth/css/normalize.css
ReactInDepth/css/popup.css
ReactInDepth/font/__init__.py
ReactInDepth/font/fontello.eot
ReactInDepth/font/fontello.svg
ReactInDepth/font/fontello.ttf
ReactInDepth/font/fontello.woff
ReactInDepth/img/__init__.py
ReactInDepth/img/annotator-glyph-sprite.png
ReactInDepth/img/annotator-icon-sprite.png
ReactInDepth/img/apple-touch-icon.png
ReactInDepth/img/cancelfullscreen.png
ReactInDepth/img/close.png
ReactInDepth/img/fullscreen.png
ReactInDepth/img/loader.gif
ReactInDepth/img/menu-icon.png
ReactInDepth/img/save.png
ReactInDepth/img/saved.png
ReactInDepth/img/settings-s.png
ReactInDepth/img/settings.png
ReactInDepth/img/star.png
ReactInDepth/js/__init__.py
ReactInDepth/js/epub.js
ReactInDepth/js/epub.min.js
ReactInDepth/js/epub.min.map
ReactInDepth/js/hooks.min.js
ReactInDepth/js/hooks.min.map
ReactInDepth/js/reader.js
ReactInDepth/js/reader.js.map
ReactInDepth/js/reader.min.js
ReactInDepth/js/reader.min.map
ReactInDepth/js/hooks/__init__.py
ReactInDepth/js/hooks/extensions/__init__.py
ReactInDepth/js/hooks/extensions/highlight.js
ReactInDepth/js/libs/__init__.py
ReactInDepth/js/libs/jquery.min.js
ReactInDepth/js/libs/localforage.min.js
ReactInDepth/js/libs/screenfull.js
ReactInDepth/js/libs/screenfull.min.js
ReactInDepth/js/libs/zip.min.js
ReactInDepth/js/plugins/__init__.py
ReactInDepth/js/plugins/hypothesis.js
ReactInDepth/js/plugins/search.js
react_in_depth-2024.3.2.0.dist-info/METADATA
react_in_depth-2024.3.2.0.dist-info/WHEEL
react_in_depth-2024.3.2.0.dist-info/entry_points.txt
react_in_depth-2024.3.2.0.dist-info/top_level.txt
react_in_depth-2024.3.2.0.dist-info/RECORD
